cervmongo/__init__.py
cervmongo/_version.py
cervmongo/aio.py
cervmongo/config.py
cervmongo/main.py
cervmongo/models.py
cervmongo/utils.py
cervmongo/vars.py
cervmongo/extra/__init__.py
cervmongo/extra/convenience.py
cervmongo/extra/datatables.py
cervmongo/extra/examples.py
cervmongo-0.2.4.dist-info/LICENSE
cervmongo-0.2.4.dist-info/METADATA
cervmongo-0.2.4.dist-info/WHEEL
cervmongo-0.2.4.dist-info/top_level.txt
cervmongo-0.2.4.dist-info/RECORD
