Metadata-Version: 2.1
Name: cervmongo
Version: 0.2.4
Summary: An (even) higher-level MongoDB client
Home-page: https://github.com/antcer1213/cervmongo
Author: Anthony 'antcer1213' Cervantes
Author-email: anthony.cervantes@cerver.info
License: UNKNOWN
Project-URL: Bug Tracker, https://github.com/antcer1213/cervmongo/issues
Project-URL: Documentation, https://cerver.info/packages/cervmongo/
Project-URL: Source Code, https://cerver.info/packages/cervmongo/_modules/
Project-URL: Repository, https://github.com/antcer1213/cervmongo
Keywords: motor pymongo mongodb database nonsql db mongo
Platform: UNKNOWN
Classifier: Programming Language :: Python :: 3
Classifier: License :: OSI Approved :: MIT License
Classifier: Operating System :: OS Independent
Requires-Python: >=3.6
Requires-Dist: dataclasses
Requires-Dist: jsonschema
Requires-Dist: pymongo (<4,>=3.12)
Requires-Dist: python-dateutil
Requires-Dist: uuid
Provides-Extra: aio
Requires-Dist: motor ; extra == 'aio'
Provides-Extra: all
Requires-Dist: marshmallow ; extra == 'all'
Requires-Dist: motor ; extra == 'all'
Requires-Dist: pydantic ; extra == 'all'
Requires-Dist: python-dotenv ; extra == 'all'
Requires-Dist: python-magic ; extra == 'all'
Provides-Extra: extra
Requires-Dist: marshmallow ; extra == 'extra'
Requires-Dist: pydantic ; extra == 'extra'
Requires-Dist: python-magic ; extra == 'extra'
Provides-Extra: settings
Requires-Dist: python-dotenv ; extra == 'settings'
